.gitignore
LICENSE
MANIFEST.in
README.md
setup.py
.github/ISSUE_TEMPLATE.md
.github/PULL_REQUEST_TEMPLATE.md
BlueWhale3_DataFusion.egg-info/PKG-INFO
BlueWhale3_DataFusion.egg-info/SOURCES.txt
BlueWhale3_DataFusion.egg-info/dependency_links.txt
BlueWhale3_DataFusion.egg-info/entry_points.txt
BlueWhale3_DataFusion.egg-info/namespace_packages.txt
BlueWhale3_DataFusion.egg-info/not-zip-safe
BlueWhale3_DataFusion.egg-info/requires.txt
BlueWhale3_DataFusion.egg-info/top_level.txt
doc/Makefile
doc/conf.py
doc/index.rst
doc/make.bat
doc/data-yeast/gene_annotations.tab
doc/data-yeast/gene_expression.tab
doc/data-yeast/gene_interactions.tab
doc/data-yeast/gene_literature.tab
doc/data-yeast/gene_pathways.tab
doc/data-yeast/literature_go.tab
doc/data-yeast/literature_topics.tab
doc/data-yeast/ontology_structure.tab
doc/widgets/IMDbactors.rst
doc/widgets/chaining.rst
doc/widgets/completionscoring.rst
doc/widgets/fusiongraph.rst
doc/widgets/latentfactors.rst
doc/widgets/matrixsampler.rst
doc/widgets/meanfuser.rst
doc/widgets/moviegenres.rst
doc/widgets/movieratings.rst
doc/widgets/tabletorelation.rst
doc/widgets/icons/chaining.png
doc/widgets/icons/completion-scoring.png
doc/widgets/icons/fusion-graph.png
doc/widgets/icons/imdb-actors.png
doc/widgets/icons/latent-factors.png
doc/widgets/icons/matrix-sampler.png
doc/widgets/icons/mean-fuser.png
doc/widgets/icons/movie-genres.png
doc/widgets/icons/movie-ratings.png
doc/widgets/icons/table-to-relation.png
doc/widgets/images/Chaining-Example.png
doc/widgets/images/Chaining1-stamped.png
doc/widgets/images/Chaining1-tags.txt
doc/widgets/images/Chaining1.png
doc/widgets/images/CompletionScoring-Example.png
doc/widgets/images/CompletionScoring-stamped.png
doc/widgets/images/CompletionScoring-tags.txt
doc/widgets/images/CompletionScoring.png
doc/widgets/images/FusionGraph-Example.png
doc/widgets/images/FusionGraph1-stamped.png
doc/widgets/images/FusionGraph1-tags.txt
doc/widgets/images/FusionGraph1.png
doc/widgets/images/IMDbActors-Example.png
doc/widgets/images/IMDbActors-stamped.png
doc/widgets/images/IMDbActors-tags.txt
doc/widgets/images/IMDbActors.png
doc/widgets/images/LatentFactors-Example.png
doc/widgets/images/LatentFactors1-stamped.png
doc/widgets/images/LatentFactors1-tags.txt
doc/widgets/images/LatentFactors1.png
doc/widgets/images/MatrixSampler-Example2.png
