Metadata-Version: 1.0
Name: BlueWhale3-DataFusion
Version: 0.1.11
Summary: Orange DataFusion add-on.
Home-page: https://github.com/biolab/orange3-datafusion
Author: 大圣实验楼
Author-email: dashenglab@163.com
License: UNKNOWN
Keywords: data mining,orange3 add-on
Platform: UNKNOWN
